prefect_cwl/__init__.py
prefect_cwl/constants.py
prefect_cwl/exceptions.py
prefect_cwl/flow_builder.py
prefect_cwl/io.py
prefect_cwl/logger.py
prefect_cwl/models.py
prefect_cwl/backends/__init__.py
prefect_cwl/backends/base.py
prefect_cwl/backends/docker.py
prefect_cwl/backends/k8s.py
prefect_cwl/backends/types.py
prefect_cwl/planner/__init__.py
prefect_cwl/planner/planner.py
prefect_cwl/planner/templates.py
prefect_cwl-0.1.0.dist-info/METADATA
prefect_cwl-0.1.0.dist-info/WHEEL
prefect_cwl-0.1.0.dist-info/top_level.txt
prefect_cwl-0.1.0.dist-info/RECORD
