Metadata-Version: 2.1
Name: prefect-cwl
Version: 0.1.0
Summary: Orchestrate CWL with Prefect
Author-email: Francesco Bruni <bruni@planetek.it>, Domenico Monaco <monaco@planetek.it>, Paolo Minel <minel@planetek.it>, Giuseppe Mastrogiacomo <mastrogiacomo@planetek.it>
Requires-Python: >=3.13
Requires-Dist: prefect>=3.6.13
Requires-Dist: pydantic>=2.12.5
Requires-Dist: yml>=0.0.1
Provides-Extra: docker
Requires-Dist: prefect-docker>=0.7.1; extra == "docker"
Provides-Extra: k8s
Requires-Dist: prefect-kubernetes>=0.7.2; extra == "k8s"
Requires-Dist: kubernetes>=34.1.0; extra == "k8s"
